mcp_outlook-0.1.16.dist-info/licenses/LICENSE
mcp_outlook_server/__init__.py
mcp_outlook_server/clean_utils.py
mcp_outlook_server/common.py
mcp_outlook_server/format_utils.py
mcp_outlook_server/format_utils_search.py
mcp_outlook_server/resources.py
mcp_outlook_server/server.py
mcp_outlook_server/tools.py
mcp_outlook-0.1.16.dist-info/METADATA
mcp_outlook-0.1.16.dist-info/WHEEL
mcp_outlook-0.1.16.dist-info/entry_points.txt
mcp_outlook-0.1.16.dist-info/top_level.txt
mcp_outlook-0.1.16.dist-info/RECORD
