Metadata-Version: 2.4
Name: mcp-outlook
Version: 0.1.16
Summary: MCP Server to integrate with outlook
Author: sofias tech
Requires-Python: >=3.10
License-File: LICENSE
Requires-Dist: mcp>=1.6.0
Requires-Dist: office365-rest-python-client>=2.6.1
Requires-Dist: python-dotenv>=1.1.0
Requires-Dist: requests>=2.32.3
Requires-Dist: html2text>=2020.1.16
Requires-Dist: beautifulsoup4>=4.12.2
Requires-Dist: inscriptis>=2.3.2
Requires-Dist: lxml>=4.9.3
Dynamic: license-file
